binlookup/__init__.py
binlookup/client.py
binlookup-0.1.0.dist-info/METADATA
binlookup-0.1.0.dist-info/WHEEL
binlookup-0.1.0.dist-info/top_level.txt
binlookup-0.1.0.dist-info/RECORD
